morpho_ga/__init__.py
morpho_ga/ga_search.py
morpho_ga-1.0.0.dist-info/METADATA
morpho_ga-1.0.0.dist-info/WHEEL
morpho_ga-1.0.0.dist-info/licenses/LICENSE
morpho_ga-1.0.0.dist-info/RECORD
