Metadata-Version: 2.3
Name: morpho-ga
Version: 1.0.0
Summary: GA Client Component of the Morpho Design Explorer Project. This client provides the `GASearch` class interface to connect to a MorphoDesignExplorer backend, load project schemas and existing generated models, and generate new children with custom fitness functions.
Project-URL: Homepage, https://github.com/MorphoDesignExplorer/morpho-ga/
Author-email: Krishna Sivakumar <krishnasivaprogrammer@gmail.com>
License-File: LICENSE
Classifier: Operating System :: OS Independent
Classifier: Programming Language :: Python :: 3
Requires-Python: >=3.8
Requires-Dist: morpho-typing<2,>=1.5.0
Requires-Dist: requests==2.31.0
Requires-Dist: tinydb==4.8.0
